ChineseTimeNLP/__init__.py
ChineseTimeNLP/enums.py
ChineseTimeNLP/normalizer.py
ChineseTimeNLP/point.py
ChineseTimeNLP/result.py
ChineseTimeNLP/unit.py
ChineseTimeNLP/helpers/LunarSolarConverter.py
ChineseTimeNLP/helpers/__init__.py
ChineseTimeNLP/helpers/arrow_helper.py
ChineseTimeNLP/helpers/int_common.py
ChineseTimeNLP/helpers/str_common.py
ChineseTimeNLP/resource/__init__.py
ChineseTimeNLP/resource/holiday.py
ChineseTimeNLP/resource/pattern.py
ChineseTimeNLP/tests/__init__.py
ChineseTimeNLP/tests/conftest.py
ChineseTimeNLP/tests/test_normalizer.py
ChineseTimeNLP/tests/test_point.py
ChineseTimeNLP/tests/test_utils.py
ChineseTimeNLP-3.0.1.dist-info/METADATA
ChineseTimeNLP-3.0.1.dist-info/WHEEL
ChineseTimeNLP-3.0.1.dist-info/top_level.txt
ChineseTimeNLP-3.0.1.dist-info/RECORD
