Metadata-Version: 2.1
Name: ChineseTimeNLP
Version: 3.0.1
Summary: 将中文时间表达词转为相应的时间字符串，支持时间点，时间段，时间间隔。
Home-page: https://github.com/KelabDev/ChineseTimeNLP
Author: Artin
Author-email: lengthmin@gmail.com
License: MIT Licence
Keywords: nlp,time nlp
Platform: UNKNOWN
Classifier: Programming Language :: Python :: 3.7
Requires-Dist: arrow
Requires-Dist: loguru
Requires-Dist: regex
